luckyrobots/__init__.py
luckyrobots/client.py
luckyrobots/luckyrobots.py
luckyrobots/utils.py
luckyrobots/config/__init__.py
luckyrobots/config/robots.yaml
luckyrobots/engine/__init__.py
luckyrobots/engine/check_updates.py
luckyrobots/engine/download.py
luckyrobots/engine/manager.py
luckyrobots/grpc/__init__.py
luckyrobots/grpc/generated/__init__.py
luckyrobots/grpc/generated/agent_pb2.py
luckyrobots/grpc/generated/agent_pb2_grpc.py
luckyrobots/grpc/generated/camera_pb2.py
luckyrobots/grpc/generated/camera_pb2_grpc.py
luckyrobots/grpc/generated/common_pb2.py
luckyrobots/grpc/generated/common_pb2_grpc.py
luckyrobots/grpc/generated/hazel_rpc_pb2.py
luckyrobots/grpc/generated/hazel_rpc_pb2_grpc.py
luckyrobots/grpc/generated/media_pb2.py
luckyrobots/grpc/generated/media_pb2_grpc.py
luckyrobots/grpc/generated/mujoco_pb2.py
luckyrobots/grpc/generated/mujoco_pb2_grpc.py
luckyrobots/grpc/generated/scene_pb2.py
luckyrobots/grpc/generated/scene_pb2_grpc.py
luckyrobots/grpc/generated/telemetry_pb2.py
luckyrobots/grpc/generated/telemetry_pb2_grpc.py
luckyrobots/grpc/generated/viewport_pb2.py
luckyrobots/grpc/generated/viewport_pb2_grpc.py
luckyrobots/grpc/proto/agent.proto
luckyrobots/grpc/proto/camera.proto
luckyrobots/grpc/proto/common.proto
luckyrobots/grpc/proto/hazel_rpc.proto
luckyrobots/grpc/proto/media.proto
luckyrobots/grpc/proto/mujoco.proto
luckyrobots/grpc/proto/scene.proto
luckyrobots/grpc/proto/telemetry.proto
luckyrobots/grpc/proto/viewport.proto
luckyrobots/models/__init__.py
luckyrobots/models/camera.py
luckyrobots/models/observation.py
luckyrobots/models/randomization.py
luckyrobots-0.1.72.dist-info/METADATA
luckyrobots-0.1.72.dist-info/WHEEL
luckyrobots-0.1.72.dist-info/licenses/LICENSE
luckyrobots-0.1.72.dist-info/RECORD
