Metadata-Version: 2.4
Name: luckyrobots
Version: 0.1.72
Summary: Robotics-AI Training in Hyperrealistic Game Environments
Project-URL: Homepage, https://github.com/luckyrobots/luckyrobots
Project-URL: Documentation, https://luckyrobots.readthedocs.io
Project-URL: Repository, https://github.com/luckyrobots/luckyrobots
Project-URL: Issues, https://github.com/luckyrobots/luckyrobots/issues
Author-email: Devrim Yasar <braces.verbose03@icloud.com>, Ethan Clark <ethan@luckyrobots.com>
License-Expression: MIT
License-File: LICENSE
Classifier: License :: OSI Approved :: MIT License
Classifier: Operating System :: OS Independent
Classifier: Programming Language :: Python :: 3
Classifier: Programming Language :: Python :: 3.10
Classifier: Programming Language :: Python :: 3.11
Classifier: Programming Language :: Python :: 3.12
Requires-Python: >=3.10
Requires-Dist: beautifulsoup4>=4.12.0
Requires-Dist: grpcio>=1.60.0
Requires-Dist: numpy>=1.24.0
Requires-Dist: opencv-python>=4.8.0
Requires-Dist: packaging>=23.0
Requires-Dist: protobuf>=4.25.0
Requires-Dist: psutil>=5.9.0
Requires-Dist: pydantic>=2.0.0
Requires-Dist: pyyaml>=6.0
Requires-Dist: requests>=2.31.0
Requires-Dist: tqdm>=4.66.0
Requires-Dist: watchdog>=3.0.0
